ripiu/cmsplugin_filer_video/__init__.py
ripiu/cmsplugin_filer_video/apps.py
ripiu/cmsplugin_filer_video/cms_plugins.py
ripiu/cmsplugin_filer_video/models.py
ripiu/cmsplugin_filer_video/locale/.DS_Store
ripiu/cmsplugin_filer_video/locale/it/.DS_Store
ripiu/cmsplugin_filer_video/locale/it/LC_MESSAGES/django.mo
ripiu/cmsplugin_filer_video/locale/it/LC_MESSAGES/django.po
ripiu/cmsplugin_filer_video/migrations/0001_initial.py
ripiu/cmsplugin_filer_video/migrations/__init__.py
ripiu/cmsplugin_filer_video/migrations/__pycache__/0001_initial.cpython-36.pyc
ripiu/cmsplugin_filer_video/migrations/__pycache__/__init__.cpython-36.pyc
ripiu/cmsplugin_filer_video/templates/ripiu/cmsplugin_filer_video/video.html
ripiu.cmsplugin_filer_video-0.0.1.dist-info/DESCRIPTION.rst
ripiu.cmsplugin_filer_video-0.0.1.dist-info/METADATA
ripiu.cmsplugin_filer_video-0.0.1.dist-info/RECORD
ripiu.cmsplugin_filer_video-0.0.1.dist-info/WHEEL
ripiu.cmsplugin_filer_video-0.0.1.dist-info/metadata.json
ripiu.cmsplugin_filer_video-0.0.1.dist-info/top_level.txt
